localagi/__init__.py
localagi/__main__.py
localagi/model.py
localagi/parameters.h5
localagi-1.1.0.dist-info/LICENSE
localagi-1.1.0.dist-info/METADATA
localagi-1.1.0.dist-info/WHEEL
localagi-1.1.0.dist-info/entry_points.txt
localagi-1.1.0.dist-info/top_level.txt
localagi-1.1.0.dist-info/RECORD
