Metadata-Version: 2.1
Name: localagi
Version: 1.1.0
Summary: Experience local Artificial General Intelligence.
Home-page: https://github.com/hallvardnmbu/localagi.git
Author: Hallvard Høyland Lavik
License: MIT
Classifier: Development Status :: 4 - Beta
Classifier: License :: OSI Approved :: MIT License
Classifier: Programming Language :: Python :: 3.11
Requires-Python: >=3.9
License-File: LICENSE
Requires-Dist: torch
Requires-Dist: numpy
